weather_utils/__init__.py
weather_utils/dynamodb_utils.py
weather_utils/other_helpers.py
weather_utils/sns_alerts.py
weather_utils-2.0.1.dist-info/METADATA
weather_utils-2.0.1.dist-info/WHEEL
weather_utils-2.0.1.dist-info/top_level.txt
weather_utils-2.0.1.dist-info/RECORD
