Metadata-Version: 2.4
Name: weather_utils
Version: 2.0.1
Summary: A utility package for weather data handling with AWS services
Home-page: https://github.com/sriharikata/Weather-Utils/tree/main/weather_utils
Author: Srihari Kata
Author-email: x24155331@student.ncirl.ie
Classifier: Programming Language :: Python :: 3
Classifier: License :: OSI Approved :: MIT License
Classifier: Operating System :: OS Independent
Requires-Python: >=3.7
Requires-Dist: requests
Requires-Dist: boto3
Requires-Dist: python-dotenv
Dynamic: author
Dynamic: author-email
Dynamic: classifier
Dynamic: description
Dynamic: description-content-type
Dynamic: home-page
Dynamic: requires-dist
Dynamic: requires-python
Dynamic: summary
